diffusionism/__init__.py
diffusionism/diffusion/__init__.py
diffusionism/diffusion/losses.py
diffusionism/diffusion/diffusers/__init__.py
diffusionism/diffusion/diffusers/diffuser.py
diffusionism/diffusion/hyperparameters/__init__.py
diffusionism/diffusion/hyperparameters/core.py
diffusionism/diffusion/hyperparameters/implicit_hyperparameters.py
diffusionism/diffusion/parameterizations/__init__.py
diffusionism/diffusion/parameterizations/parameterizations.py
diffusionism/diffusion/parameterizations/linear/__init__.py
diffusionism/diffusion/parameterizations/linear/conventional/__init__.py
diffusionism/diffusion/parameterizations/linear/conventional/conventional.py
diffusionism/diffusion/parameterizations/linear/essential/__init__.py
diffusionism/diffusion/parameterizations/linear/essential/essential.py
diffusionism/diffusion/samplers/__init__.py
diffusionism/diffusion/samplers/sampler.py
diffusionism/diffusion/samplers/sampling_progress.py
diffusionism/diffusion/schedules/__init__.py
diffusionism/diffusion/schedules/diffusion_schedule.py
diffusionism/diffusion/schedules/linear_schedule.py
diffusionism/diffusion/schedules/context/__init__.py
diffusionism/diffusion/schedules/context/core.py
diffusionism/diffusion/schedules/context/core.pyi
diffusionism/diffusion/schedules/context/tensor_context.py
diffusionism/diffusion/schedules/context/distributions/__init__.py
diffusionism/diffusion/schedules/context/distributions/distributions.py
diffusionism/diffusion/schedules/context/sequencings/__init__.py
diffusionism/diffusion/schedules/context/sequencings/sequencings.py
diffusionism/diffusion/unification/__init__.py
diffusionism/diffusion/unification/diffusion.py
diffusionism/diffusion/unification/diffusion_model.py
diffusionism/diffusion/utils/__init__.py
diffusionism/diffusion/utils/data_type.py
diffusionism/diffusion/utils/functions.py
diffusionism/diffusion/utils/range_clipper.py
diffusionism/methods/__init__.py
diffusionism-0.0.1b9.dist-info/licenses/LICENSE
diffusionism-0.0.1b9.dist-info/METADATA
diffusionism-0.0.1b9.dist-info/WHEEL
diffusionism-0.0.1b9.dist-info/top_level.txt
diffusionism-0.0.1b9.dist-info/RECORD
