Metadata-Version: 2.4
Name: diffusionism
Version: 0.0.1b9
Summary: Diffusionism is a Python library for rapid prototyping and deployment of diffusion models. It provides a flexible, inheritance-based architecture, allowing easy integration of new methods, with built-in pipelines for training and inference. It accelerates development and ensures reproducibility by separating general mechanics from model-specific logic.
Author-email: Caewinix <Caewinix@yeah.net>
Project-URL: Homepage, https://github.com/Caewinix/diffusionism
Project-URL: Bug Tracker, https://github.com/Caewinix/diffusionism/issues
Classifier: Programming Language :: Python :: 3
Classifier: License :: OSI Approved :: MIT License
Classifier: Operating System :: OS Independent
Requires-Python: >=3.7
License-File: LICENSE
Requires-Dist: torch>=2.0.0
Requires-Dist: numpy
Requires-Dist: torchflint>=0.0.1b10
Requires-Dist: pipelight>=0.0.1b5
Dynamic: license-file
